middle_schema/__init__.py
middle_schema/openapi.py
middle_schema/skel.py
middle_schema/utils.py
middle_schema-0.2.0.dist-info/METADATA
middle_schema-0.2.0.dist-info/RECORD
middle_schema-0.2.0.dist-info/WHEEL
middle_schema-0.2.0.dist-info/top_level.txt
