Metadata-Version: 2.1
Name: middle-schema
Version: 0.2.0
Summary: Translate your middle model declarations to OpenAPI, JSONSchema or any other schema you need
Home-page: https://github.com/vltr/middle-schema
Author: Richard Kuesters
Author-email: rkuesters@gmail.com
License: MIT license
Keywords: middle,models,hooks,customizable,openapi,swagger,jsonschema,schema
Platform: UNKNOWN
Classifier: Development Status :: 3 - Alpha
Classifier: Intended Audience :: Developers
Classifier: License :: OSI Approved :: MIT License
Classifier: Operating System :: Unix
Classifier: Operating System :: POSIX
Classifier: Operating System :: Microsoft :: Windows
Classifier: Programming Language :: Python
Classifier: Programming Language :: Python :: 3.5
Classifier: Programming Language :: Python :: 3.6
Classifier: Programming Language :: Python :: 3.7
Classifier: Programming Language :: Python :: Implementation :: CPython
Classifier: Topic :: Utilities
Requires-Dist: middle (>=0.2.0)
